README.rst
setup.py
django_metamodel.egg-info/PKG-INFO
django_metamodel.egg-info/SOURCES.txt
django_metamodel.egg-info/dependency_links.txt
django_metamodel.egg-info/requires.txt
django_metamodel.egg-info/top_level.txt
metamodel/__init__.py
metamodel/admin.py
metamodel/models.py
metamodel/tests.py
metamodel/migrations/0001_initial.py
metamodel/migrations/__init__.py